django_changelog
