Metadata-Version: 1.1
Name: django-changelog
Version: 0.1.2
Summary: A simple Django app to display a CHANGELOG.md file as a url.
Home-page: https://github.com/jonbesga/django-changelog
Author: Jon Besga
Author-email: jonan.bsg@gmail.com
License: MIT
Platform: UNKNOWN
Classifier: Environment :: Web Environment
Classifier: Framework :: Django
Classifier: Framework :: Django :: 2.2
Classifier: Intended Audience :: Developers
Classifier: License :: OSI Approved :: MIT License
Classifier: Operating System :: OS Independent
Classifier: Programming Language :: Python
Classifier: Programming Language :: Python :: 3.5
Classifier: Programming Language :: Python :: 3.6
Classifier: Topic :: Internet :: WWW/HTTP
Classifier: Topic :: Internet :: WWW/HTTP :: Dynamic Content
